{
    "Ar36": {
        "error": 0.00025467470714566926, 
        "fit": "previous", 
        "references": [
            {
                "exclude": false, 
                "record_id": "bu-FD-F-541"
            }
        ], 
        "value": 0.010698082853093016
    }, 
    "Ar37": {
        "error": 0.0112779817149823, 
        "fit": "previous", 
        "references": [
            {
                "exclude": false, 
                "record_id": "bu-FD-F-541"
            }
        ], 
        "value": 0.010494320450198508
    }, 
    "Ar38": {
        "error": 0.012167285887101082, 
        "fit": "previous", 
        "references": [
            {
                "exclude": false, 
                "record_id": "bu-FD-F-541"
            }
        ], 
        "value": -0.009126246347686884
    }, 
    "Ar39": {
        "error": 0.022715064849546773, 
        "fit": "previous", 
        "references": [
            {
                "exclude": false, 
                "record_id": "bu-FD-F-541"
            }
        ], 
        "value": -0.013337420984795059
    }, 
    "Ar40": {
        "error": 0.018738850797051187, 
        "fit": "previous", 
        "references": [
            {
                "exclude": false, 
                "record_id": "bu-FD-F-541"
            }
        ], 
        "value": 3.087962026124054
    }
}