{
    "Ar36": {
        "error": 0.0006832718807266847, 
        "filter_outliers_dict": {
            "filter_outliers": true, 
            "iterations": 2, 
            "std_devs": 2
        }, 
        "fit": "Parabolic", 
        "value": 0.1132858656948325
    }, 
    "Ar37": {
        "error": 0.013590612064663799, 
        "filter_outliers_dict": {
            "filter_outliers": true, 
            "iterations": 2, 
            "std_devs": 2
        }, 
        "fit": "linear", 
        "value": 35.473963863517405
    }, 
    "Ar38": {
        "error": 0.01268732984279434, 
        "filter_outliers_dict": {
            "filter_outliers": true, 
            "iterations": 2, 
            "std_devs": 2
        }, 
        "fit": "linear", 
        "value": 0.14719345287662045
    }, 
    "Ar39": {
        "error": 0.02392513400103595, 
        "filter_outliers_dict": {
            "filter_outliers": true, 
            "iterations": 2, 
            "std_devs": 2
        }, 
        "fit": "Parabolic", 
        "value": 14.013393711606437
    }, 
    "Ar40": {
        "error": 0.024160739546086687, 
        "filter_outliers_dict": {
            "filter_outliers": true, 
            "iterations": 2, 
            "std_devs": 2
        }, 
        "fit": "Parabolic", 
        "value": 58.12188128871223
    }
}