{
    "Ar36": {
        "error": 0.0010218589798047003, 
        "filter_outliers_dict": {
            "filter_outliers": true, 
            "iterations": 2, 
            "std_devs": 2
        }, 
        "fit": "Parabolic", 
        "value": 0.21946662075161755
    }, 
    "Ar37": {
        "error": 0.013574804797818474, 
        "filter_outliers_dict": {
            "filter_outliers": true, 
            "iterations": 2, 
            "std_devs": 2
        }, 
        "fit": "linear", 
        "value": 31.73314940420361
    }, 
    "Ar38": {
        "error": 0.013007991145081015, 
        "filter_outliers_dict": {
            "filter_outliers": true, 
            "iterations": 2, 
            "std_devs": 2
        }, 
        "fit": "linear", 
        "value": 0.23564994918937998
    }, 
    "Ar39": {
        "error": 0.024844778321760245, 
        "filter_outliers_dict": {
            "filter_outliers": true, 
            "iterations": 2, 
            "std_devs": 2
        }, 
        "fit": "Parabolic", 
        "value": 24.127890893956224
    }, 
    "Ar40": {
        "error": 0.023281739806674518, 
        "filter_outliers_dict": {
            "filter_outliers": true, 
            "iterations": 2, 
            "std_devs": 2
        }, 
        "fit": "Parabolic", 
        "value": 73.61090903543318
    }
}