{
    "AX": {
        "error": 0.011303911549818609, 
        "filter_outliers_dict": {
            "filter_outliers": true, 
            "iterations": 1, 
            "std_devs": 2
        }, 
        "fit": "average", 
        "value": -0.11245879261014356
    }, 
    "H1": {
        "error": 0.012425410899730633, 
        "filter_outliers_dict": {
            "filter_outliers": true, 
            "iterations": 1, 
            "std_devs": 2
        }, 
        "fit": "average", 
        "value": -0.02769367798621679
    }, 
    "H2": {
        "error": 0.010400768334206547, 
        "filter_outliers_dict": {
            "filter_outliers": true, 
            "iterations": 1, 
            "std_devs": 2
        }, 
        "fit": "average", 
        "value": -0.021101388542664752
    }, 
    "L1": {
        "error": 0.009823776775747728, 
        "filter_outliers_dict": {
            "filter_outliers": true, 
            "iterations": 1, 
            "std_devs": 2
        }, 
        "fit": "average", 
        "value": -0.16822813319141713
    }, 
    "L2(CDD)": {
        "error": 5.06538655136947e-06, 
        "filter_outliers_dict": {
            "filter_outliers": true, 
            "iterations": 1, 
            "std_devs": 2
        }, 
        "fit": "average", 
        "value": 2.2463528321651284e-05
    }
}