{
    "Ar36": {
        "error": 0.0034347568018368324, 
        "filter_outliers_dict": {
            "filter_outliers": true, 
            "iterations": 2, 
            "std_devs": 2
        }, 
        "fit": "Parabolic", 
        "value": 3.0070451351224374
    }, 
    "Ar37": {
        "error": 0.011636386386508794, 
        "filter_outliers_dict": {
            "filter_outliers": true, 
            "iterations": 2, 
            "std_devs": 2
        }, 
        "fit": "linear", 
        "value": -0.12568039011689006
    }, 
    "Ar38": {
        "error": 0.013149455492990085, 
        "filter_outliers_dict": {
            "filter_outliers": true, 
            "iterations": 2, 
            "std_devs": 2
        }, 
        "fit": "linear", 
        "value": 0.46156499843059307
    }, 
    "Ar39": {
        "error": 0.021626156204933755, 
        "filter_outliers_dict": {
            "filter_outliers": true, 
            "iterations": 2, 
            "std_devs": 2
        }, 
        "fit": "Parabolic", 
        "value": -0.03754841137630131
    }, 
    "Ar40": {
        "error": 0.06612127257245938, 
        "filter_outliers_dict": {
            "filter_outliers": true, 
            "iterations": 2, 
            "std_devs": 2
        }, 
        "fit": "Parabolic", 
        "value": 884.7924657229667
    }
}