{
    "Ar36": {
        "error": 0.0005678306431052008, 
        "filter_outliers_dict": {
            "filter_outliers": true, 
            "iterations": 2, 
            "std_devs": 2
        }, 
        "fit": "Parabolic", 
        "value": 0.0492739315564682
    }, 
    "Ar37": {
        "error": 0.011843392061016691, 
        "filter_outliers_dict": {
            "filter_outliers": true, 
            "iterations": 2, 
            "std_devs": 2
        }, 
        "fit": "linear", 
        "value": -0.1661514610912166
    }, 
    "Ar38": {
        "error": 0.01269884792800704, 
        "filter_outliers_dict": {
            "filter_outliers": true, 
            "iterations": 2, 
            "std_devs": 2
        }, 
        "fit": "linear", 
        "value": 1.58713994159752
    }, 
    "Ar39": {
        "error": 0.03271216626458652, 
        "filter_outliers_dict": {
            "filter_outliers": true, 
            "iterations": 2, 
            "std_devs": 2
        }, 
        "fit": "Parabolic", 
        "value": 127.96867638787504
    }, 
    "Ar40": {
        "error": 0.07834930152435146, 
        "filter_outliers_dict": {
            "filter_outliers": true, 
            "iterations": 2, 
            "std_devs": 2
        }, 
        "fit": "Parabolic", 
        "value": 1582.683787018677
    }
}